turu/version.py
turu-0.13.2.dist-info/METADATA
turu-0.13.2.dist-info/WHEEL
turu-0.13.2.dist-info/RECORD
