Metadata-Version: 2.3
Name: turu
Version: 0.13.2
Summary: Simple Typed Python Database Client based PEP 249
Author: yassun7010
Author-email: yassun7010@outlook.com
Requires-Python: >=3.9,<4.0
Classifier: Development Status :: 4 - Beta
Classifier: Intended Audience :: Developers
Classifier: License :: OSI Approved :: MIT License
Classifier: Programming Language :: Python :: 3
Classifier: Programming Language :: Python :: 3.9
Classifier: Programming Language :: Python :: 3.10
Classifier: Programming Language :: Python :: 3.11
Classifier: Programming Language :: Python :: 3.12
Classifier: Programming Language :: Python :: 3.13
Classifier: Programming Language :: Python :: 3 :: Only
Classifier: Programming Language :: SQL
Classifier: Topic :: Database
Classifier: Topic :: Scientific/Engineering :: Information Analysis
Classifier: Topic :: Software Development
Classifier: Topic :: Software Development :: Libraries
Classifier: Topic :: Software Development :: Libraries :: Application Frameworks
Classifier: Topic :: Software Development :: Libraries :: Python Modules
Provides-Extra: bigquery
Provides-Extra: mysql
Provides-Extra: postgres
Provides-Extra: snowflake
Provides-Extra: sqlite3
Requires-Dist: turu-bigquery (==0.13.2) ; extra == "bigquery"
Requires-Dist: turu-core (==0.13.2)
Requires-Dist: turu-mysql (==0.13.2) ; extra == "mysql"
Requires-Dist: turu-postgres (==0.13.2) ; extra == "postgres"
Requires-Dist: turu-snowflake (==0.13.2) ; extra == "snowflake"
Requires-Dist: turu-sqlite3 (==0.13.2) ; extra == "sqlite3"
Project-URL: Documentation, https://yassun7010.github.io/turu-py/
Project-URL: Repository, https://github.com/yassun7010/turu-py
